
<?xml version="1.0" encoding="UTF-8"?>
<mxfile host="app.diagrams.net">
  <diagram id="ERD-LRS" name="ERD & LRS">
    <mxGraphModel dx="1000" dy="1000" grid="1" gridSize="10" guides="1" tooltips="1" connect="1" arrows="1" fold="1" page="1" pageScale="1" pageWidth="2000" pageHeight="2000" math="0" shadow="0">
      <root>
        <mxCell id="0" />
        <mxCell id="1" parent="0" />
        <!-- Minimal node agar pasti tampil -->
        <mxCell id="2" value="nasabah" style="rounded=1;whiteSpace=wrap;html=1;fillColor=#e1f5fe;strokeColor=#0277bd;" vertex="1" parent="1">
          <mxGeometry x="40" y="40" width="120" height="60" as="geometry" />
        </mxCell>
        <mxCell id="3" value="saldo" style="rounded=1;whiteSpace=wrap;html=1;fillColor=#fffde7;strokeColor=#fbc02d;" vertex="1" parent="1">
          <mxGeometry x="220" y="40" width="120" height="60" as="geometry" />
        </mxCell>
        <mxCell id="4" value="transaksi" style="rounded=1;whiteSpace=wrap;html=1;fillColor=#e8f5e9;strokeColor=#388e3c;" vertex="1" parent="1">
          <mxGeometry x="40" y="140" width="120" height="60" as="geometry" />
        </mxCell>
        <mxCell id="5" value="petugas" style="rounded=1;whiteSpace=wrap;html=1;fillColor=#fce4ec;strokeColor=#ad1457;" vertex="1" parent="1">
          <mxGeometry x="220" y="140" width="120" height="60" as="geometry" />
        </mxCell>
        <!-- Minimal relasi -->
        <mxCell id="6" style="edgeStyle=orthogonalEdgeStyle;rounded=0;orthogonalLoop=1;jettySize=auto;html=1;endArrow=block;endFill=1;strokeColor=#0277bd;" edge="1" parent="1" source="2" target="3">
          <mxGeometry relative="1" as="geometry" />
        </mxCell>
        <mxCell id="7" style="edgeStyle=orthogonalEdgeStyle;rounded=0;orthogonalLoop=1;jettySize=auto;html=1;endArrow=block;endFill=1;strokeColor=#388e3c;" edge="1" parent="1" source="4" target="5">
          <mxGeometry relative="1" as="geometry" />
        </mxCell>
      </root>
    </mxGraphModel>
  </diagram>
</mxfile>
